pelk_screen/__init__.py
pelk_screen-0.0.5.dist-info/METADATA
pelk_screen-0.0.5.dist-info/WHEEL
pelk_screen-0.0.5.dist-info/top_level.txt
pelk_screen-0.0.5.dist-info/RECORD
